qbertclient/__init__.py
qbertclient/dict_utils.py
qbertclient/exceptions.py
qbertclient/keystone.py
qbertclient/qbert.py
qbertclient/request_utils.py
qbertclient-0.0.11.dist-info/LICENSE
qbertclient-0.0.11.dist-info/METADATA
qbertclient-0.0.11.dist-info/WHEEL
qbertclient-0.0.11.dist-info/top_level.txt
qbertclient-0.0.11.dist-info/RECORD
