Metadata-Version: 2.1
Name: qbertclient
Version: 0.0.11
Summary: Platform9 Qbert client
Home-page: https://github.com/platform9/qbertclient
Author: Vann Teves
Author-email: vann@platform9.com
License: Apache License 2.0
Platform: UNKNOWN
Classifier: Programming Language :: Python :: 3
Classifier: Operating System :: OS Independent
Requires-Python: >=3.5
Requires-Dist: requests
